reece/__init__.py
reece-0.0.0.dist-info/DESCRIPTION.rst
reece-0.0.0.dist-info/METADATA
reece-0.0.0.dist-info/RECORD
reece-0.0.0.dist-info/WHEEL
reece-0.0.0.dist-info/metadata.json
reece-0.0.0.dist-info/top_level.txt
reece-0.0.0.dist-info/zip-safe
