Metadata-Version: 2.0
Name: reece
Version: 0.0.0
Summary: ensures that the `reece` package is available only as a namespace package
Home-page: https://github.com/reece/reece-namespace-declaration
Author: Reece Hart <reecehart@gmail.com>
Author-email: UNKNOWN
License: UNKNOWN
Platform: UNKNOWN
